plzz/__init__.py
plzz/__main__.py
plzz/commands/__init__.py
plzz/commands/development_tasks/__init__.py
plzz/commands/development_tasks/licenses.py
plzz/commands/development_tasks/minify_json.py
plzz/commands/development_tasks/rename_functions.py
plzz/commands/development_tasks/upload_to_gist.py
plzz/commands/file_operations/__init__.py
plzz/commands/file_operations/check_hash.py
plzz/commands/file_operations/count_words.py
plzz/commands/file_operations/create_random_text_files.py
plzz/commands/file_operations/find_urls.py
plzz/commands/file_operations/format_sentences.py
plzz/commands/file_operations/generate_toc.py
plzz/commands/file_operations/lorem_ipsum_file.py
plzz/commands/file_operations/offensive_words.py
plzz/commands/folder_organizations/__init__.py
plzz/commands/folder_organizations/add_extension.py
plzz/commands/folder_organizations/delete_duplicates.py
plzz/commands/folder_organizations/delete_empty_files.py
plzz/commands/folder_organizations/organize_audio_by_bits.py
plzz/commands/folder_organizations/rename_files.py
plzz/commands/folder_organizations/replace_word.py
plzz/commands/utilities/__init__.py
plzz/commands/utilities/bing_wallpapers.py
plzz/commands/utilities/extract_codeblocks_markdown.py
plzz/commands/utilities/generate_password.py
plzz/commands/utilities/qrcode.py
plzz/helper_functions/__init__.py
plzz/helper_functions/commands_database.py
plzz/helper_functions/helper_functions.py
plzz/helper_functions/snippets.py
plzz_cli-0.2.dist-info/DESCRIPTION.rst
plzz_cli-0.2.dist-info/METADATA
plzz_cli-0.2.dist-info/RECORD
plzz_cli-0.2.dist-info/WHEEL
plzz_cli-0.2.dist-info/entry_points.txt
plzz_cli-0.2.dist-info/metadata.json
plzz_cli-0.2.dist-info/top_level.txt
