Metadata-Version: 2.0
Name: plzz-cli
Version: 0.2
Summary: A CLI to automate daily tasks of common and advanced users.
Home-page: https://github.com/deep5050/plzz
Author: Dipankar Pal
Author-email: dipankarpal5050@gmail.com
License: MIT
Project-URL: Source, https://github.com/deep5050/plzz/
Project-URL: Upstream, https://github.com/deep5050/plzz/
Keywords: CLI automation file-operations file-organization tasks system-tools app
Platform: any
Classifier: License :: OSI Approved :: MIT License
Classifier: Development Status :: 5 - Production/Stable
Classifier: Environment :: Console
Classifier: Programming Language :: Python :: 3
Classifier: Operating System :: OS Independent
Classifier: Intended Audience :: End Users/Desktop
Classifier: Topic :: Utilities
Requires-Python: >=3.6
Requires-Dist: fire (==0.5.0)
Requires-Dist: python-magic (==0.4.27)
Requires-Dist: qrcode (==7.3.1)
Requires-Dist: termcolor (==1.1.0)
